LICENSE
MANIFEST.in
README.md
pyproject.toml
requirements.txt
setup.py
spec.md
python_dev_toolkit/__init__.py
python_dev_toolkit/core.py
python_dev_toolkit.egg-info/PKG-INFO
python_dev_toolkit.egg-info/SOURCES.txt
python_dev_toolkit.egg-info/dependency_links.txt
python_dev_toolkit.egg-info/top_level.txt