Metadata-Version: 2.4
Name: python-dev-toolkit
Version: 0.1.9
Summary: Professional toolkit for Python developers and software engineers
Home-page: https://github.com/alex-smith/python-dev-toolkit
Author: alex-smith
Author-email: 
License: MIT
Project-URL: Homepage, https://github.com/alex-smith/python-dev-toolkit
Project-URL: Bug Reports, https://github.com/alex-smith/python-dev-toolkit/issues
Project-URL: Source, https://github.com/alex-smith/python-dev-toolkit/
Keywords: python,development,toolkit,engineering
Classifier: Development Status :: 3 - Alpha
Classifier: Intended Audience :: Education
Classifier: License :: OSI Approved :: MIT License
Classifier: Operating System :: OS Independent
Classifier: Programming Language :: Python :: 3
Classifier: Programming Language :: Python :: 3.7
Classifier: Programming Language :: Python :: 3.8
Classifier: Programming Language :: Python :: 3.9
Classifier: Programming Language :: Python :: 3.10
Classifier: Programming Language :: Python :: 3.11
Classifier: Topic :: Education
Classifier: Topic :: Software Development :: Libraries :: Python Modules
Requires-Python: >=3.7
License-File: LICENSE
Dynamic: home-page
Dynamic: license-file
Dynamic: requires-python
